Metadata-Version: 2.1
Name: django-appwrite
Version: 1.5.1
Summary: Django Middleware to authenticate users with Appwrite
Home-page: https://github.com/khashashin/django-appwrite
Author: Yusuf Khasbulatov
License: MIT
Project-URL: Documentation, https://github.com/khashashin/django-appwrite/blob/main/README.md
Project-URL: Funding, https://donate.pypi.org
Project-URL: Say Thanks!, https://patreon.com/khashashin
Project-URL: Source, https://github.com/khashashin/django-appwrite
Project-URL: Tracker, https://github.com/khashashin/django-appwrite/issues
Keywords: appwrite auth django
Classifier: Framework :: Django
Classifier: Topic :: Utilities
Classifier: License :: OSI Approved :: MIT License
Classifier: Intended Audience :: Developers
Classifier: Programming Language :: Python :: 3
Classifier: Programming Language :: Python :: 3.6
Classifier: Programming Language :: Python :: 3.7
Classifier: Programming Language :: Python :: 3.8
Classifier: Programming Language :: Python :: 3.9
Classifier: Programming Language :: Python :: 3.10
License-File: LICENSE
